[
  {
    "timestamp": 1772114400,
    "datetime": "2026-02-26 14:00:00",
    "open": 0.23666,
    "high": 0.24016,
    "low": 0.23634,
    "close": 0.23758,
    "volume": 4086.7
  },
  {
    "timestamp": 1772118000,
    "datetime": "2026-02-26 15:00:00",
    "open": 0.2394,
    "high": 0.24054,
    "low": 0.23665,
    "close": 0.24003,
    "volume": 3047.7
  },
  {
    "timestamp": 1772121600,
    "datetime": "2026-02-26 16:00:00",
    "open": 0.23839,
    "high": 0.24319,
    "low": 0.23591,
    "close": 0.23697,
    "volume": 20237.3
  },
  {
    "timestamp": 1772125200,
    "datetime": "2026-02-26 17:00:00",
    "open": 0.2377,
    "high": 0.23787,
    "low": 0.23478,
    "close": 0.23678,
    "volume": 708.5
  },
  {
    "timestamp": 1772128800,
    "datetime": "2026-02-26 18:00:00",
    "open": 0.23573,
    "high": 0.23879,
    "low": 0.23564,
    "close": 0.2387,
    "volume": 424.5
  },
  {
    "timestamp": 1772132400,
    "datetime": "2026-02-26 19:00:00",
    "open": 0.23906,
    "high": 0.24188,
    "low": 0.23906,
    "close": 0.24137,
    "volume": 1697.8
  },
  {
    "timestamp": 1772136000,
    "datetime": "2026-02-26 20:00:00",
    "open": 0.24033,
    "high": 0.24073,
    "low": 0.23918,
    "close": 0.23918,
    "volume": 350.3
  },
  {
    "timestamp": 1772139600,
    "datetime": "2026-02-26 21:00:00",
    "open": 0.23809,
    "high": 0.23809,
    "low": 0.23726,
    "close": 0.23797,
    "volume": 3902.5
  },
  {
    "timestamp": 1772143200,
    "datetime": "2026-02-26 22:00:00",
    "open": 0.23786,
    "high": 0.23811,
    "low": 0.23723,
    "close": 0.23747,
    "volume": 431.2
  },
  {
    "timestamp": 1772146800,
    "datetime": "2026-02-26 23:00:00",
    "open": 0.23616,
    "high": 0.23768,
    "low": 0.23616,
    "close": 0.23702,
    "volume": 167.0
  },
  {
    "timestamp": 1772150400,
    "datetime": "2026-02-27 00:00:00",
    "open": 0.23629,
    "high": 0.23718,
    "low": 0.23471,
    "close": 0.23718,
    "volume": 153.4
  },
  {
    "timestamp": 1772154000,
    "datetime": "2026-02-27 01:00:00",
    "open": 0.23809,
    "high": 0.23956,
    "low": 0.236,
    "close": 0.23632,
    "volume": 745.3
  },
  {
    "timestamp": 1772157600,
    "datetime": "2026-02-27 02:00:00",
    "open": 0.23781,
    "high": 0.23972,
    "low": 0.2355,
    "close": 0.23551,
    "volume": 2490.7
  },
  {
    "timestamp": 1772161200,
    "datetime": "2026-02-27 03:00:00",
    "open": 0.23549,
    "high": 0.23596,
    "low": 0.23521,
    "close": 0.23596,
    "volume": 440.8
  },
  {
    "timestamp": 1772164800,
    "datetime": "2026-02-27 04:00:00",
    "open": 0.23821,
    "high": 0.23879,
    "low": 0.23636,
    "close": 0.23879,
    "volume": 652.0
  },
  {
    "timestamp": 1772168400,
    "datetime": "2026-02-27 05:00:00",
    "open": 0.23714,
    "high": 0.23994,
    "low": 0.23714,
    "close": 0.23787,
    "volume": 2418.6
  },
  {
    "timestamp": 1772172000,
    "datetime": "2026-02-27 06:00:00",
    "open": 0.23782,
    "high": 0.23793,
    "low": 0.23535,
    "close": 0.23537,
    "volume": 755.4
  },
  {
    "timestamp": 1772175600,
    "datetime": "2026-02-27 07:00:00",
    "open": 0.23544,
    "high": 0.23544,
    "low": 0.23478,
    "close": 0.23542,
    "volume": 17528.8
  },
  {
    "timestamp": 1772179200,
    "datetime": "2026-02-27 08:00:00",
    "open": 0.23764,
    "high": 0.23784,
    "low": 0.23451,
    "close": 0.23524,
    "volume": 31922.4
  },
  {
    "timestamp": 1772182800,
    "datetime": "2026-02-27 09:00:00",
    "open": 0.23524,
    "high": 0.23728,
    "low": 0.23418,
    "close": 0.23578,
    "volume": 14210.8
  },
  {
    "timestamp": 1772186400,
    "datetime": "2026-02-27 10:00:00",
    "open": 0.23459,
    "high": 0.23581,
    "low": 0.2324,
    "close": 0.23283,
    "volume": 7364.2
  },
  {
    "timestamp": 1772190000,
    "datetime": "2026-02-27 11:00:00",
    "open": 0.23327,
    "high": 0.23373,
    "low": 0.23147,
    "close": 0.23162,
    "volume": 563.5
  },
  {
    "timestamp": 1772193600,
    "datetime": "2026-02-27 12:00:00",
    "open": 0.23116,
    "high": 0.23132,
    "low": 0.23007,
    "close": 0.23122,
    "volume": 2896.9
  },
  {
    "timestamp": 1772197200,
    "datetime": "2026-02-27 13:00:00",
    "open": 0.23133,
    "high": 0.23133,
    "low": 0.23004,
    "close": 0.23015,
    "volume": 1828.3
  },
  {
    "timestamp": 1772200800,
    "datetime": "2026-02-27 14:00:00",
    "open": 0.23332,
    "high": 0.23633,
    "low": 0.23332,
    "close": 0.23472,
    "volume": 3230.2
  },
  {
    "timestamp": 1772204400,
    "datetime": "2026-02-27 15:00:00",
    "open": 0.23459,
    "high": 0.23848,
    "low": 0.23459,
    "close": 0.23542,
    "volume": 1777.5
  },
  {
    "timestamp": 1772208000,
    "datetime": "2026-02-27 16:00:00",
    "open": 0.23478,
    "high": 0.24044,
    "low": 0.23478,
    "close": 0.23794,
    "volume": 3712.6
  },
  {
    "timestamp": 1772211600,
    "datetime": "2026-02-27 17:00:00",
    "open": 0.23823,
    "high": 0.24002,
    "low": 0.23241,
    "close": 0.23241,
    "volume": 3708.9
  },
  {
    "timestamp": 1772215200,
    "datetime": "2026-02-27 18:00:00",
    "open": 0.23273,
    "high": 0.23463,
    "low": 0.23273,
    "close": 0.23273,
    "volume": 737.4
  },
  {
    "timestamp": 1772218800,
    "datetime": "2026-02-27 19:00:00",
    "open": 0.23269,
    "high": 0.23456,
    "low": 0.23078,
    "close": 0.23398,
    "volume": 2472.6
  },
  {
    "timestamp": 1772222400,
    "datetime": "2026-02-27 20:00:00",
    "open": 0.234,
    "high": 0.234,
    "low": 0.23253,
    "close": 0.23253,
    "volume": 586.1
  },
  {
    "timestamp": 1772226000,
    "datetime": "2026-02-27 21:00:00",
    "open": 0.23272,
    "high": 0.23272,
    "low": 0.23143,
    "close": 0.23173,
    "volume": 898.2
  },
  {
    "timestamp": 1772229600,
    "datetime": "2026-02-27 22:00:00",
    "open": 0.23274,
    "high": 0.23274,
    "low": 0.22902,
    "close": 0.23161,
    "volume": 56311.8
  },
  {
    "timestamp": 1772233200,
    "datetime": "2026-02-27 23:00:00",
    "open": 0.23205,
    "high": 0.23348,
    "low": 0.23141,
    "close": 0.23157,
    "volume": 3972.6
  },
  {
    "timestamp": 1772236800,
    "datetime": "2026-02-28 00:00:00",
    "open": 0.23222,
    "high": 0.23942,
    "low": 0.23222,
    "close": 0.23869,
    "volume": 12154.4
  },
  {
    "timestamp": 1772240400,
    "datetime": "2026-02-28 01:00:00",
    "open": 0.23857,
    "high": 0.23909,
    "low": 0.23412,
    "close": 0.23412,
    "volume": 7952.0
  },
  {
    "timestamp": 1772244000,
    "datetime": "2026-02-28 02:00:00",
    "open": 0.23333,
    "high": 0.23521,
    "low": 0.23241,
    "close": 0.23241,
    "volume": 2022.7
  },
  {
    "timestamp": 1772247600,
    "datetime": "2026-02-28 03:00:00",
    "open": 0.23283,
    "high": 0.23439,
    "low": 0.23083,
    "close": 0.23439,
    "volume": 14673.2
  },
  {
    "timestamp": 1772251200,
    "datetime": "2026-02-28 04:00:00",
    "open": 0.23419,
    "high": 0.23521,
    "low": 0.23294,
    "close": 0.23308,
    "volume": 3167.0
  },
  {
    "timestamp": 1772254800,
    "datetime": "2026-02-28 05:00:00",
    "open": 0.23182,
    "high": 0.23182,
    "low": 0.23035,
    "close": 0.23035,
    "volume": 1067.9
  },
  {
    "timestamp": 1772258400,
    "datetime": "2026-02-28 06:00:00",
    "open": 0.23014,
    "high": 0.23095,
    "low": 0.21813,
    "close": 0.21893,
    "volume": 24282.2
  },
  {
    "timestamp": 1772262000,
    "datetime": "2026-02-28 07:00:00",
    "open": 0.22005,
    "high": 0.22356,
    "low": 0.21937,
    "close": 0.22168,
    "volume": 5440.6
  },
  {
    "timestamp": 1772265600,
    "datetime": "2026-02-28 08:00:00",
    "open": 0.21916,
    "high": 0.21916,
    "low": 0.21645,
    "close": 0.21787,
    "volume": 1209.5
  },
  {
    "timestamp": 1772269200,
    "datetime": "2026-02-28 09:00:00",
    "open": 0.21829,
    "high": 0.21861,
    "low": 0.21735,
    "close": 0.21861,
    "volume": 201.3
  },
  {
    "timestamp": 1772272800,
    "datetime": "2026-02-28 10:00:00",
    "open": 0.21575,
    "high": 0.21701,
    "low": 0.21485,
    "close": 0.21519,
    "volume": 1949.7
  },
  {
    "timestamp": 1772276400,
    "datetime": "2026-02-28 11:00:00",
    "open": 0.21578,
    "high": 0.21662,
    "low": 0.21537,
    "close": 0.21621,
    "volume": 503.4
  },
  {
    "timestamp": 1772280000,
    "datetime": "2026-02-28 12:00:00",
    "open": 0.21621,
    "high": 0.21744,
    "low": 0.21535,
    "close": 0.21535,
    "volume": 1045.0
  },
  {
    "timestamp": 1772283600,
    "datetime": "2026-02-28 13:00:00",
    "open": 0.21712,
    "high": 0.222,
    "low": 0.21636,
    "close": 0.222,
    "volume": 4282.7
  },
  {
    "timestamp": 1772287200,
    "datetime": "2026-02-28 14:00:00",
    "open": 0.2224,
    "high": 0.2224,
    "low": 0.21771,
    "close": 0.21771,
    "volume": 3220.5
  },
  {
    "timestamp": 1772290800,
    "datetime": "2026-02-28 15:00:00",
    "open": 0.21892,
    "high": 0.22045,
    "low": 0.21719,
    "close": 0.21902,
    "volume": 2106.8
  },
  {
    "timestamp": 1772294400,
    "datetime": "2026-02-28 16:00:00",
    "open": 0.21906,
    "high": 0.21906,
    "low": 0.21797,
    "close": 0.21827,
    "volume": 533.4
  },
  {
    "timestamp": 1772298000,
    "datetime": "2026-02-28 17:00:00",
    "open": 0.21817,
    "high": 0.21965,
    "low": 0.21708,
    "close": 0.21963,
    "volume": 1844.9
  },
  {
    "timestamp": 1772301600,
    "datetime": "2026-02-28 18:00:00",
    "open": 0.21957,
    "high": 0.22204,
    "low": 0.21918,
    "close": 0.22179,
    "volume": 1337.0
  },
  {
    "timestamp": 1772305200,
    "datetime": "2026-02-28 19:00:00",
    "open": 0.224,
    "high": 0.22447,
    "low": 0.22253,
    "close": 0.22253,
    "volume": 447.2
  },
  {
    "timestamp": 1772308800,
    "datetime": "2026-02-28 20:00:00",
    "open": 0.22289,
    "high": 0.22541,
    "low": 0.22289,
    "close": 0.22541,
    "volume": 1033.7
  },
  {
    "timestamp": 1772312400,
    "datetime": "2026-02-28 21:00:00",
    "open": 0.22506,
    "high": 0.22506,
    "low": 0.22365,
    "close": 0.22436,
    "volume": 897.0
  },
  {
    "timestamp": 1772316000,
    "datetime": "2026-02-28 22:00:00",
    "open": 0.22534,
    "high": 0.22691,
    "low": 0.22534,
    "close": 0.22691,
    "volume": 1035.8
  },
  {
    "timestamp": 1772319600,
    "datetime": "2026-02-28 23:00:00",
    "open": 0.22576,
    "high": 0.22576,
    "low": 0.22297,
    "close": 0.22297,
    "volume": 2824.5
  },
  {
    "timestamp": 1772323200,
    "datetime": "2026-03-01 00:00:00",
    "open": 0.22232,
    "high": 0.22232,
    "low": 0.22225,
    "close": 0.22225,
    "volume": 9.0
  },
  {
    "timestamp": 1772326800,
    "datetime": "2026-03-01 01:00:00",
    "open": 0.2221,
    "high": 0.22562,
    "low": 0.21894,
    "close": 0.22308,
    "volume": 5087.2
  },
  {
    "timestamp": 1772330400,
    "datetime": "2026-03-01 02:00:00",
    "open": 0.22391,
    "high": 0.22731,
    "low": 0.22391,
    "close": 0.22505,
    "volume": 991.8
  },
  {
    "timestamp": 1772334000,
    "datetime": "2026-03-01 03:00:00",
    "open": 0.22395,
    "high": 0.22409,
    "low": 0.22329,
    "close": 0.22391,
    "volume": 481.4
  },
  {
    "timestamp": 1772337600,
    "datetime": "2026-03-01 04:00:00",
    "open": 0.22244,
    "high": 0.22381,
    "low": 0.22006,
    "close": 0.22325,
    "volume": 1445.5
  },
  {
    "timestamp": 1772341200,
    "datetime": "2026-03-01 05:00:00",
    "open": 0.22234,
    "high": 0.22284,
    "low": 0.22234,
    "close": 0.22252,
    "volume": 469.1
  },
  {
    "timestamp": 1772344800,
    "datetime": "2026-03-01 06:00:00",
    "open": 0.22055,
    "high": 0.22119,
    "low": 0.21938,
    "close": 0.21999,
    "volume": 2917.5
  },
  {
    "timestamp": 1772348400,
    "datetime": "2026-03-01 07:00:00",
    "open": 0.21965,
    "high": 0.21974,
    "low": 0.21914,
    "close": 0.21973,
    "volume": 467.4
  },
  {
    "timestamp": 1772352000,
    "datetime": "2026-03-01 08:00:00",
    "open": 0.22043,
    "high": 0.22124,
    "low": 0.21803,
    "close": 0.21825,
    "volume": 1842.1
  },
  {
    "timestamp": 1772355600,
    "datetime": "2026-03-01 09:00:00",
    "open": 0.218,
    "high": 0.21927,
    "low": 0.2174,
    "close": 0.21825,
    "volume": 1725.5
  },
  {
    "timestamp": 1772359200,
    "datetime": "2026-03-01 10:00:00",
    "open": 0.21674,
    "high": 0.21766,
    "low": 0.21674,
    "close": 0.21766,
    "volume": 695.2
  },
  {
    "timestamp": 1772362800,
    "datetime": "2026-03-01 11:00:00",
    "open": 0.21895,
    "high": 0.22005,
    "low": 0.21895,
    "close": 0.21986,
    "volume": 3224.7
  },
  {
    "timestamp": 1772366400,
    "datetime": "2026-03-01 12:00:00",
    "open": 0.21938,
    "high": 0.22014,
    "low": 0.21728,
    "close": 0.21756,
    "volume": 8417.2
  },
  {
    "timestamp": 1772370000,
    "datetime": "2026-03-01 13:00:00",
    "open": 0.21755,
    "high": 0.2212,
    "low": 0.21533,
    "close": 0.22016,
    "volume": 3345.4
  },
  {
    "timestamp": 1772373600,
    "datetime": "2026-03-01 14:00:00",
    "open": 0.21947,
    "high": 0.22023,
    "low": 0.21633,
    "close": 0.21665,
    "volume": 953.7
  },
  {
    "timestamp": 1772377200,
    "datetime": "2026-03-01 15:00:00",
    "open": 0.21714,
    "high": 0.21714,
    "low": 0.21465,
    "close": 0.21533,
    "volume": 1615.1
  },
  {
    "timestamp": 1772380800,
    "datetime": "2026-03-01 16:00:00",
    "open": 0.2167,
    "high": 0.21722,
    "low": 0.21419,
    "close": 0.21419,
    "volume": 4093.4
  },
  {
    "timestamp": 1772384400,
    "datetime": "2026-03-01 17:00:00",
    "open": 0.21645,
    "high": 0.21645,
    "low": 0.21365,
    "close": 0.21365,
    "volume": 564.9
  },
  {
    "timestamp": 1772388000,
    "datetime": "2026-03-01 18:00:00",
    "open": 0.21355,
    "high": 0.21586,
    "low": 0.21284,
    "close": 0.21295,
    "volume": 3622.9
  },
  {
    "timestamp": 1772391600,
    "datetime": "2026-03-01 19:00:00",
    "open": 0.21213,
    "high": 0.21447,
    "low": 0.21091,
    "close": 0.21091,
    "volume": 4045.2
  },
  {
    "timestamp": 1772395200,
    "datetime": "2026-03-01 20:00:00",
    "open": 0.21086,
    "high": 0.21288,
    "low": 0.20915,
    "close": 0.20915,
    "volume": 5887.4
  },
  {
    "timestamp": 1772398800,
    "datetime": "2026-03-01 21:00:00",
    "open": 0.21106,
    "high": 0.21433,
    "low": 0.21106,
    "close": 0.2129,
    "volume": 2771.2
  },
  {
    "timestamp": 1772402400,
    "datetime": "2026-03-01 22:00:00",
    "open": 0.21442,
    "high": 0.21704,
    "low": 0.21439,
    "close": 0.21439,
    "volume": 2176.1
  },
  {
    "timestamp": 1772406000,
    "datetime": "2026-03-01 23:00:00",
    "open": 0.21439,
    "high": 0.21439,
    "low": 0.21439,
    "close": 0.21439,
    "volume": 0.0
  },
  {
    "timestamp": 1772409600,
    "datetime": "2026-03-02 00:00:00",
    "open": 0.21386,
    "high": 0.21386,
    "low": 0.21161,
    "close": 0.21161,
    "volume": 1210.1
  },
  {
    "timestamp": 1772413200,
    "datetime": "2026-03-02 01:00:00",
    "open": 0.21492,
    "high": 0.21578,
    "low": 0.21482,
    "close": 0.21482,
    "volume": 226.8
  },
  {
    "timestamp": 1772416800,
    "datetime": "2026-03-02 02:00:00",
    "open": 0.21361,
    "high": 0.21825,
    "low": 0.21361,
    "close": 0.21628,
    "volume": 2406.7
  },
  {
    "timestamp": 1772420400,
    "datetime": "2026-03-02 03:00:00",
    "open": 0.21553,
    "high": 0.21967,
    "low": 0.21553,
    "close": 0.21955,
    "volume": 1488.1
  },
  {
    "timestamp": 1772424000,
    "datetime": "2026-03-02 04:00:00",
    "open": 0.21892,
    "high": 0.21892,
    "low": 0.21892,
    "close": 0.21892,
    "volume": 4.6
  },
  {
    "timestamp": 1772427600,
    "datetime": "2026-03-02 05:00:00",
    "open": 0.21824,
    "high": 0.21824,
    "low": 0.21814,
    "close": 0.21814,
    "volume": 13.2
  },
  {
    "timestamp": 1772431200,
    "datetime": "2026-03-02 06:00:00",
    "open": 0.21533,
    "high": 0.21596,
    "low": 0.21485,
    "close": 0.21596,
    "volume": 977.5
  },
  {
    "timestamp": 1772434800,
    "datetime": "2026-03-02 07:00:00",
    "open": 0.2135,
    "high": 0.214,
    "low": 0.21235,
    "close": 0.214,
    "volume": 2686.0
  },
  {
    "timestamp": 1772438400,
    "datetime": "2026-03-02 08:00:00",
    "open": 0.2124,
    "high": 0.2157,
    "low": 0.21124,
    "close": 0.2152,
    "volume": 2791.5
  },
  {
    "timestamp": 1772442000,
    "datetime": "2026-03-02 09:00:00",
    "open": 0.216,
    "high": 0.22127,
    "low": 0.216,
    "close": 0.2176,
    "volume": 7530.7
  },
  {
    "timestamp": 1772445600,
    "datetime": "2026-03-02 10:00:00",
    "open": 0.21929,
    "high": 0.22309,
    "low": 0.21864,
    "close": 0.2215,
    "volume": 1338.4
  },
  {
    "timestamp": 1772449200,
    "datetime": "2026-03-02 11:00:00",
    "open": 0.22232,
    "high": 0.22469,
    "low": 0.22074,
    "close": 0.22125,
    "volume": 6418.9
  },
  {
    "timestamp": 1772452800,
    "datetime": "2026-03-02 12:00:00",
    "open": 0.22065,
    "high": 0.22065,
    "low": 0.21714,
    "close": 0.21965,
    "volume": 46034.4
  },
  {
    "timestamp": 1772456400,
    "datetime": "2026-03-02 13:00:00",
    "open": 0.21811,
    "high": 0.21908,
    "low": 0.21606,
    "close": 0.21698,
    "volume": 3298.8
  },
  {
    "timestamp": 1772460000,
    "datetime": "2026-03-02 14:00:00",
    "open": 0.218,
    "high": 0.22219,
    "low": 0.2167,
    "close": 0.22219,
    "volume": 394.4
  },
  {
    "timestamp": 1772463600,
    "datetime": "2026-03-02 15:00:00",
    "open": 0.22252,
    "high": 0.22545,
    "low": 0.22217,
    "close": 0.22438,
    "volume": 2699.5
  },
  {
    "timestamp": 1772467200,
    "datetime": "2026-03-02 16:00:00",
    "open": 0.22489,
    "high": 0.22701,
    "low": 0.22332,
    "close": 0.22534,
    "volume": 2770.2
  },
  {
    "timestamp": 1772470800,
    "datetime": "2026-03-02 17:00:00",
    "open": 0.22361,
    "high": 0.22361,
    "low": 0.22307,
    "close": 0.22307,
    "volume": 13.5
  }
]